philosophese/__init__.py
philosophese-0.0.1.dist-info/LICENSE
philosophese-0.0.1.dist-info/METADATA
philosophese-0.0.1.dist-info/WHEEL
philosophese-0.0.1.dist-info/top_level.txt
philosophese-0.0.1.dist-info/RECORD
