Metadata-Version: 2.1
Name: philosophese
Version: 0.0.1
Summary: 输入中文，他会将它转化为哲♂学的语言。Chinese -> “哲♂学” Language
Author-email: Lafcadia <chuishenx@oblivionocean.top>
Project-URL: Homepage, https://github.com/Lafcadia/philosophese
Project-URL: Issues, https://github.com/Lafcadia/philosophese/issues
Classifier: Programming Language :: Python :: 3
Classifier: License :: OSI Approved :: MIT License
Classifier: Operating System :: OS Independent
Requires-Python: >=3.8
License-File: LICENSE
